{"list":" bg-stone-100 flex flex-col h-screen w-screen z-10 flex-row h-full w-full w-1/2 h-1/2 items-end justify-end -mb-25 m-2 m-5 ml-10 items-start mt-20 text-3xl pb-2.5 absolute bottom-0 h-3/12 left-0 z-20 mb-4 ml-4 text-9xl text-left xl:text-[15rem]","map":{"bg-stone-100":true,"flex":true,"flex-col":true,"h-screen":true,"w-screen":true,"z-10":true,"flex-row":true,"h-full":true,"w-full":true,"w-1/2":true,"h-1/2":true,"items-end":true,"justify-end":true,"-mb-25":true,"m-2":true,"m-5":true,"ml-10":true,"items-start":true,"mt-20":true,"text-3xl":true,"pb-2.5":true,"absolute":true,"bottom-0":true,"h-3/12":true,"left-0":true,"z-20":true,"mb-4":true,"ml-4":true,"text-9xl":true,"text-left":true,"xl:text-[15rem]":true}}